cloudeasy/alicloud/__init__.py
cloudeasy/alicloud/alicloud_config.py
cloudeasy/alicloud/dns_manager.py
cloudeasy/alicloud/resource_center_manager.py
cloudeasy/alicloud/tea_api.py
cloudeasy_alicloud-0.1.0.dist-info/METADATA
cloudeasy_alicloud-0.1.0.dist-info/WHEEL
cloudeasy_alicloud-0.1.0.dist-info/RECORD
