Metadata-Version: 2.1
Name: cloudeasy.alicloud
Version: 0.1.0
Summary: Some proxy for alicloud operation based on raw alicloud tea api
License: MIT
Author: Calm Zhu
Author-email: zhuqian@yirenchengtuan.com
Requires-Python: >=3.8,<4.0
Classifier: License :: OSI Approved :: MIT License
Classifier: Programming Language :: Python :: 3
Classifier: Programming Language :: Python :: 3.8
Classifier: Programming Language :: Python :: 3.9
Classifier: Programming Language :: Python :: 3.10
Classifier: Programming Language :: Python :: 3.11
Classifier: Programming Language :: Python :: 3.12
Requires-Dist: aiohttp (>=3.9.0,<4.0.0)
Requires-Dist: alibabacloud-tea-openapi (>=0.3.8,<0.4.0)
